textmetrics/__init__.py
textmetrics/common.py
textmetrics/main.py
textmetrics/bleu/__init__.py
textmetrics/bleu/bleu.py
textmetrics/custom/__init__.py
textmetrics/custom/ngrams.py
textmetrics/meteor/__init__.py
textmetrics/meteor/meteor.py
textmetrics/red/__init__.py
textmetrics/red/red.py
textmetrics/test/__init__.py
textmetrics/test/test_ngrams.py
textmetrics/utility/__init__.py
textmetrics/utility/clean.py
textmetrics/utility/storage.py
textmetrics-0.0.2.dist-info/METADATA
textmetrics-0.0.2.dist-info/RECORD
textmetrics-0.0.2.dist-info/WHEEL
textmetrics-0.0.2.dist-info/top_level.txt
