Metadata-Version: 2.1
Name: textmetrics
Version: 0.0.2
Summary: Automatic text metrics---BLEU, ROUGE, and METEOR, pllus extras like vocab and ngrams.
Home-page: https://github.com/mbforbes/textmetrics/
Author: Maxwell Forbes
Author-email: mbforbes@gmail.com
License: MIT
Keywords: text-metrics text metrics nlp bleu rouge meteor ngrams vocabulary vocab
Platform: UNKNOWN
Classifier: Development Status :: 3 - Alpha
Classifier: Intended Audience :: Developers
Classifier: License :: OSI Approved :: MIT License
Classifier: Programming Language :: Python :: 3.6
Requires-Dist: mypy-extensions (>=0.3.0)
Requires-Dist: numpy (>=1.15.0)
Requires-Dist: rouge (>=0.3.1)
Requires-Dist: six (>=1.11.0)
Requires-Dist: tabulate (>=0.8.2)
